aineko_plugins/nodes/http_poller/__init__.py
aineko_plugins/nodes/http_poller/http_poller.py
aineko_plugins/nodes/http_poller/py.typed
aineko_plugins_nodes_http_poller-0.0.3.dist-info/LICENSE
aineko_plugins_nodes_http_poller-0.0.3.dist-info/METADATA
aineko_plugins_nodes_http_poller-0.0.3.dist-info/WHEEL
aineko_plugins_nodes_http_poller-0.0.3.dist-info/RECORD
